mako2cli/DataLoader.py
mako2cli/Renderer.py
mako2cli/TemplateEngine.py
mako2cli/__init__.py
mako2cli/cli.py
mako2cli-0.1.1.dist-info/entry_points.txt
mako2cli-0.1.1.dist-info/LICENSE
mako2cli-0.1.1.dist-info/WHEEL
mako2cli-0.1.1.dist-info/METADATA
mako2cli-0.1.1.dist-info/RECORD
