Metadata-Version: 2.1
Name: mako2cli
Version: 0.1.1
Summary: Mako Template Command-Line Tool
Home-page: https://github.com/fbagagli/mako2cli
License: MIT
Keywords: mako,template,cli
Author: fbagagli
Author-email: francesco.bagagli@gmail.com
Requires-Python: >=3.7,<4.0
Classifier: License :: OSI Approved :: MIT License
Classifier: Programming Language :: Python :: 3
Classifier: Programming Language :: Python :: 3.7
Classifier: Programming Language :: Python :: 3.8
Requires-Dist: attrs (>=19.3.0,<20.0.0)
Requires-Dist: click (>=7.1.2,<8.0.0)
Requires-Dist: importlib_metadata (>=1.7.0,<2.0.0); python_version < "3.8"
Requires-Dist: mako (>=1.1.3,<2.0.0)
Requires-Dist: pyyaml (>=5.3.1,<6.0.0)
Project-URL: Documentation, https://mako2cli.readthedocs.io
Project-URL: Repository, https://github.com/fbagagli/mako2cli
